eust/__init__.py
eust/cli.py
eust/core.py
eust/nuts.py
eust/tables/__init__.py
eust/tables/data.py
eust/tables/metadata.py
eust/tables/scrape.py
eust-0.5.4.dist-info/AUTHORS.rst
eust-0.5.4.dist-info/LICENSE
eust-0.5.4.dist-info/METADATA
eust-0.5.4.dist-info/WHEEL
eust-0.5.4.dist-info/entry_points.txt
eust-0.5.4.dist-info/top_level.txt
eust-0.5.4.dist-info/RECORD
