Metadata-Version: 2.1
Name: eust
Version: 0.5.4
Summary: A set of tools to download, archive, and read Eurostat data
Home-page: https://github.com/rasmuse/eust
Author: Rasmus Einarsson
Author-email: mr@rasmuseinarsson.se
License: MIT license
Keywords: eust
Platform: UNKNOWN
Classifier: Development Status :: 2 - Pre-Alpha
Classifier: Intended Audience :: Developers
Classifier: License :: OSI Approved :: MIT License
Classifier: Natural Language :: English
Classifier: Programming Language :: Python :: 3
Classifier: Programming Language :: Python :: 3.6
Classifier: Programming Language :: Python :: 3.7
Classifier: Programming Language :: Python :: 3.8
Requires-Dist: Click (>=7.0)
Requires-Dist: pandas (>=0.24)
Requires-Dist: tables (>=3.2)
Requires-Dist: pandasdmx (>=0.9)
Requires-Dist: requests (>=2.5.1)
Requires-Dist: yaconf (==0.2)
Requires-Dist: xlrd (>=1.0)
